setup.py
aioyoyo/__init__.py
aioyoyo/client.py
aioyoyo/cmdhandler.py
aioyoyo/helpers.py
aioyoyo/protocol.py
aioyoyo.egg-info/PKG-INFO
aioyoyo.egg-info/SOURCES.txt
aioyoyo.egg-info/dependency_links.txt
aioyoyo.egg-info/top_level.txt
aioyoyo/oyoyo/__init__.py
aioyoyo/oyoyo/client.py
aioyoyo/oyoyo/cmdhandler.py
aioyoyo/oyoyo/examplebot.py
aioyoyo/oyoyo/helpers.py
aioyoyo/oyoyo/ircevents.py
aioyoyo/oyoyo/parse.py
aioyoyo/oyoyo/services.py