Metadata-Version: 1.1
Name: aioyoyo
Version: 1.2.4
Summary: An Asyncio oyoyo port
Home-page: https://github.com/henry232323/aioyoyo
Author: henry232323
Author-email: henry@rhodochrosite.xyz
License: GPL
Keywords: IRC Asyncio
Platform: UNKNOWN
Classifier: Development Status :: 5 - Production/Stable
Classifier: Intended Audience :: Developers
Classifier: Topic :: Communications :: Chat :: Internet Relay Chat
Classifier: License :: OSI Approved :: MIT License
Classifier: Programming Language :: Python :: 3.5
Classifier: Programming Language :: Python :: 3.6
